TwitterHandler/VERSION
TwitterHandler/__init__.py
TwitterHandler/Kafka/__init__.py
TwitterHandler/Kafka/stream.py
TwitterHandler-1.1.1.dist-info/METADATA
TwitterHandler-1.1.1.dist-info/WHEEL
TwitterHandler-1.1.1.dist-info/top_level.txt
TwitterHandler-1.1.1.dist-info/RECORD
