Metadata-Version: 2.1
Name: TwitterHandler
Version: 1.1.1
Summary: A simple Twitter handler for the Twitter API.
Home-page: https://github.com/HassanRady/TwitterHandler
Author: Hassan Rady
Author-email: hassan.khaled.rady@gmail.com
License: MIT license
Keywords: Tweets
Classifier: Development Status :: 2 - Pre-Alpha
Classifier: Intended Audience :: Developers
Classifier: License :: OSI Approved :: MIT License
Classifier: Natural Language :: English
Classifier: Programming Language :: Python :: 3
Classifier: Programming Language :: Python :: 3.6
Classifier: Programming Language :: Python :: 3.7
Classifier: Programming Language :: Python :: 3.8
Requires-Python: >=3.9.0
Requires-Dist: kafka-python (==2.0.2)
Requires-Dist: tweepy (==4.10.0)
Requires-Dist: python-dotenv (==0.20.0)
